<?xml version="1.0" encoding="UTF-8"?>

<!-- generated on 2024-01-07 11:34:26 by Eclipse SUMO GUI Version 1.18.0
<configuration xmlns:xsi="http://www.w3.org/2001/XMLSchema-instance" xsi:noNamespaceSchemaLocation="http://sumo.dlr.de/xsd/sumoConfiguration.xsd">

    <input>
        <net-file value="map/sumo_map/mcity.net.xml"/>
        <route-files value="map/sumo_map/mcity.route.xml"/>
        <additional-files value="map/sumo_map/mcity.add.xml"/>
    </input>

    <time>
        <begin value="0"/>
        <end value="86400"/>
        <step-length value="0.05"/>
    </time>

    <processing>
        <lateral-resolution value="0.25"/>
        <collision.action value="warn"/>
        <collision.check-junctions value="true"/>
        <collision.mingap-factor value="0"/>
        <scale value="1"/>
        <time-to-teleport value="300"/>
    </processing>

    <traci_server>
        <remote-port value="50893"/>
    </traci_server>

    <random_number>
        <random value="true"/>
    </random_number>

</configuration>
-->

<meandata xmlns:xsi="http://www.w3.org/2001/XMLSchema-instance" xsi:noNamespaceSchemaLocation="http://sumo.dlr.de/xsd/meandata_file.xsd">
    <interval begin="0.00" end="10.50" id="dump_lane">
        <edge id="EG_1_3_1">
            <lane id="EG_1_3_1_0" sampledSeconds="21.70" traveltime="56.40" overlapTraveltime="57.53" density="8.27" laneDensity="8.27" occupancy="4.14" waitingTime="0.45" timeLoss="7.72" speed="4.43" speedRelative="0.55" departed="3" arrived="0" entered="0" left="0" laneChangedFrom="0" laneChangedTo="0"/>
            <lane id="EG_1_3_1_1" sampledSeconds="17.90" traveltime="43.17" overlapTraveltime="44.03" density="6.82" laneDensity="6.82" occupancy="3.41" waitingTime="0.25" timeLoss="5.87" speed="5.79" speedRelative="0.72" departed="2" arrived="0" entered="0" left="0" laneChangedFrom="0" laneChangedTo="0"/>
        </edge>
        <edge id="EG_22_1_1">
            <lane id="EG_22_1_1_0" sampledSeconds="20.03" traveltime="11.13" overlapTraveltime="12.34" density="52.05" laneDensity="52.05" occupancy="25.37" waitingTime="0.45" timeLoss="7.27" speed="3.38" speedRelative="0.68" departed="3" arrived="0" entered="0" left="1" laneChangedFrom="0" laneChangedTo="0"/>
        </edge>
        <edge id="EG_23_2_1">
            <lane id="EG_23_2_1_0" sampledSeconds="21.50" traveltime="13.79" overlapTraveltime="15.17" density="41.06" laneDensity="41.06" occupancy="20.53" waitingTime="0.45" timeLoss="8.33" speed="3.62" speedRelative="0.60" departed="3" arrived="0" entered="0" left="0" laneChangedFrom="0" laneChangedTo="0"/>
        </edge>
        <edge id="EG_24_1_1">
            <lane id="EG_24_1_1_0" sampledSeconds="16.71" traveltime="10.27" overlapTraveltime="11.58" density="46.69" laneDensity="46.69" occupancy="22.49" waitingTime="0.30" timeLoss="4.49" speed="3.37" speedRelative="0.67" departed="2" arrived="0" entered="0" left="1" laneChangedFrom="0" laneChangedTo="0"/>
        </edge>
        <edge id="EG_25_2_1">
            <lane id="EG_25_2_1_0" sampledSeconds="20.67" traveltime="11.59" overlapTraveltime="12.68" density="45.53" laneDensity="45.53" occupancy="22.26" waitingTime="0.50" timeLoss="6.58" speed="3.81" speedRelative="0.76" departed="3" arrived="0" entered="0" left="1" laneChangedFrom="0" laneChangedTo="0"/>
        </edge>
        <edge id="EG_27_1_1">
            <lane id="EG_27_1_1_0" sampledSeconds="10.45" traveltime="15.53" overlapTraveltime="19.68" density="53.28" laneDensity="53.28" occupancy="26.64" waitingTime="2.80" timeLoss="7.78" speed="1.20" speedRelative="0.24" departed="1" arrived="0" entered="0" left="0" laneChangedFrom="0" laneChangedTo="0"/>
        </edge>
        <edge id="EG_27_2_1">
            <lane id="EG_27_2_1_0" sampledSeconds="5.44" overlapTraveltime="3.37" density="120.77" laneDensity="120.77" occupancy="48.70" waitingTime="0.80" timeLoss="3.65" speed="1.84" speedRelative="0.31" departed="2" arrived="0" entered="0" left="2" laneChangedFrom="0" laneChangedTo="0"/>
        </edge>
        <edge id="EG_27_2_2">
            <lane id="EG_27_2_2_0" sampledSeconds="5.61" traveltime="6.16" overlapTraveltime="8.10" density="33.71" laneDensity="33.71" occupancy="14.77" waitingTime="0.00" timeLoss="3.00" speed="2.58" speedRelative="0.52" departed="0" arrived="0" entered="1" left="0" laneChangedFrom="0" laneChangedTo="0"/>
        </edge>
        <edge id="EG_27_3_1">
            <lane id="EG_27_3_1_0" sampledSeconds="7.11" traveltime="7.90" overlapTraveltime="11.73" density="65.57" laneDensity="65.57" occupancy="29.80" waitingTime="1.50" timeLoss="5.30" speed="1.31" speedRelative="0.26" departed="0" arrived="0" entered="1" left="0" laneChangedFrom="0" laneChangedTo="0"/>
        </edge>
        <edge id="EG_5_2_1">
            <lane id="EG_5_2_1_0" sampledSeconds="10.76" traveltime="6.12" overlapTraveltime="7.00" density="60.06" laneDensity="60.06" occupancy="27.00" waitingTime="0.30" timeLoss="3.80" speed="3.15" speedRelative="0.63" departed="2" arrived="0" entered="0" left="2" laneChangedFrom="0" laneChangedTo="0"/>
        </edge>
        <edge id="EG_5_2_11">
            <lane id="EG_5_2_11_0" sampledSeconds="2.63" traveltime="5.39" overlapTraveltime="6.43" density="9.62" laneDensity="9.62" occupancy="3.89" waitingTime="0.00" timeLoss="0.16" speed="4.83" speedRelative="0.97" departed="0" arrived="0" entered="1" left="0" laneChangedFrom="0" laneChangedTo="0"/>
        </edge>
        <edge id="EG_6_1_1">
            <lane id="EG_6_1_1_0" sampledSeconds="10.45" traveltime="20.02" overlapTraveltime="27.85" density="77.87" laneDensity="77.87" occupancy="38.94" waitingTime="4.40" timeLoss="8.50" speed="0.64" speedRelative="0.21" departed="1" arrived="0" entered="0" left="0" laneChangedFrom="0" laneChangedTo="0"/>
        </edge>
        <edge id="EG_6_2_1">
            <lane id="EG_6_2_1_0" sampledSeconds="10.45" traveltime="20.31" overlapTraveltime="28.38" density="79.11" laneDensity="79.11" occupancy="39.56" waitingTime="4.40" timeLoss="8.31" speed="0.62" speedRelative="0.21" departed="1" arrived="0" entered="0" left="0" laneChangedFrom="0" laneChangedTo="0"/>
        </edge>
        <edge id="gneE6">
            <lane id="gneE6_0" sampledSeconds="2.86" traveltime="1.52" overlapTraveltime="2.86" density="47.25" laneDensity="47.25" occupancy="12.12" waitingTime="0.00" timeLoss="0.76" speed="3.76" speedRelative="0.75" departed="0" arrived="0" entered="1" left="1" laneChangedFrom="0" laneChangedTo="0"/>
        </edge>
    </interval>
</meandata>
